django_simple_menu-2.1.4.dist-info/licenses/LICENSE
menu/__init__.py
menu/menu.py
menu/templates/bootstrap-navbar-submenu.html
menu/templates/bootstrap-navbar.html
menu/templatetags/__init__.py
menu/templatetags/menu.py
simple_menu/__init__.py
simple_menu/menu.py
simple_menu/test_settings.py
simple_menu/templates/simple_menu/bootstrap-navbar-submenu.html
simple_menu/templates/simple_menu/bootstrap-navbar.html
simple_menu/templatetags/__init__.py
simple_menu/templatetags/simple_menu.py
simple_menu/tests/__init__.py
simple_menu/tests/test_menu.py
django_simple_menu-2.1.4.dist-info/METADATA
django_simple_menu-2.1.4.dist-info/WHEEL
django_simple_menu-2.1.4.dist-info/top_level.txt
django_simple_menu-2.1.4.dist-info/RECORD
